README.rst
httpcompressionserver.py
setup.py
httpcompressionserver.egg-info/PKG-INFO
httpcompressionserver.egg-info/SOURCES.txt
httpcompressionserver.egg-info/dependency_links.txt
httpcompressionserver.egg-info/top_level.txt