Metadata-Version: 1.1
Name: httpcompressionserver
Version: 0.4
Summary: Add support of HTTP compression to standard library module http.server
Home-page: https://github.com/PierreQuentel/httpcompressionserver
Author: Pierre Quentel
Author-email: quentel.pierre@orange.fr
License: BSD
Keywords: Python HTTP server compression
Platform: UNKNOWN
Classifier: Intended Audience :: Developers
Classifier: Topic :: Internet :: WWW/HTTP :: HTTP Servers
Classifier: Operating System :: OS Independent
Classifier: License :: OSI Approved :: BSD License
Classifier: Programming Language :: Python :: 3
